white_rabbit/__init__.py
white_rabbit/vectorized_backtest.py
white_rabbit-0.0.3.dist-info/DESCRIPTION.rst
white_rabbit-0.0.3.dist-info/METADATA
white_rabbit-0.0.3.dist-info/RECORD
white_rabbit-0.0.3.dist-info/WHEEL
white_rabbit-0.0.3.dist-info/metadata.json
white_rabbit-0.0.3.dist-info/top_level.txt
