Metadata-Version: 2.0
Name: white-rabbit
Version: 0.0.3
Summary: Vectorized summary stats computation
Home-page: https://github.com/predata/white-rabbit
Author: Predata
Author-email: dev@predata.com
License: UNKNOWN
Platform: UNKNOWN
Requires-Dist: numpy (>=1.11.0)
Requires-Dist: pandas (>=0.18.0)
